CHANGES.txt
LICENSE.txt
MANIFEST.in
README.rst
image_LICENSE_Nuvola.txt
setup.py
etsdemo/__init__.py
etsdemo/app.py
etsdemo/info.py
etsdemo/loader.py
etsdemo/main.py
etsdemo/version.py
etsdemo.egg-info/PKG-INFO
etsdemo.egg-info/SOURCES.txt
etsdemo.egg-info/dependency_links.txt
etsdemo.egg-info/entry_points.txt
etsdemo.egg-info/requires.txt
etsdemo.egg-info/top_level.txt
etsdemo/images/enthought-icon.png
etsdemo/images/next.png
etsdemo/images/parent.png
etsdemo/images/previous.png
etsdemo/images/reload.png
etsdemo/images/run.png
etsdemo/tests/__init__.py
etsdemo/tests/test_app.py
etsdemo/tests/test_info.py
etsdemo/tests/test_loader.py
etsdemo/tests/test_main.py
etsdemo/tests/testing.py