Metadata-Version: 2.1
Name: etsdemo
Version: 0.1.0
Summary: Enthought Tool Suite Demo Application
Home-page: https://github.com/enthought/traitsui
Author: Enthought
Author-email: info@enthought.com
License: BSD
Platform: UNKNOWN
Classifier: Development Status :: 1 - Planning
Classifier: Intended Audience :: Developers
Classifier: Intended Audience :: Science/Research
Classifier: License :: OSI Approved :: BSD License
Classifier: Operating System :: MacOS
Classifier: Operating System :: Microsoft :: Windows
Classifier: Operating System :: OS Independent
Classifier: Operating System :: POSIX
Classifier: Operating System :: Unix
Classifier: Programming Language :: Python
Classifier: Programming Language :: Python :: 3.5
Classifier: Programming Language :: Python :: 3.6
Classifier: Programming Language :: Python :: 3.7
Classifier: Programming Language :: Python :: 3.8
Classifier: Topic :: Scientific/Engineering
Classifier: Topic :: Software Development
Requires-Python: >=3.5
Provides-Extra: wx
Provides-Extra: pyqt5
Provides-Extra: pyside2
Provides-Extra: test
